dbgym/__init__.py
dbgym/config.py
dbgym/dataset.py
dbgym/db.py
dbgym/db2graph.py
dbgym/logger.py
dbgym/loss.py
dbgym/model.py
dbgym/optimizer.py
dbgym/register.py
dbgym/run.py
dbgym/train.py
dbgym/config/config_gcn.yaml
dbgym/config/config_mlp.yaml
dbgym/config/config_xgboost.yaml
dbgym/contribute/__init__.py
dbgym/contribute/example.py
dbgym/models/gnn.py
dbgym/models/heterognn.py
dbgym/models/mlp.py
dbgym/models/xgb.py
dbgym/utils/device.py
dbgym/utils/seed.py
dbgym-0.1.3.dist-info/METADATA
dbgym-0.1.3.dist-info/WHEEL
dbgym-0.1.3.dist-info/licenses/LICENSE
dbgym-0.1.3.dist-info/RECORD
