Metadata-Version: 2.1
Name: dbgym
Version: 0.1.3
Summary: DBGym: platform for ML research and application on databases
Project-URL: Homepage, https://github.com/JiaxuanYou/DBGym
Project-URL: Bug Tracker, https://github.com/JiaxuanYou/DBGym/issues
Author-email: DBGym Team <dbgym@googlegroups.com>
License-Expression: MIT
License-File: LICENSE
Classifier: Intended Audience :: Science/Research
Classifier: License :: OSI Approved :: MIT License
Classifier: Operating System :: OS Independent
Classifier: Programming Language :: Python :: 3.8
Classifier: Topic :: Scientific/Engineering :: Artificial Intelligence
Requires-Python: >=3.8
Requires-Dist: numpy
Requires-Dist: pandas
Requires-Dist: requests
Requires-Dist: scikit-learn
Requires-Dist: tensorboard
Requires-Dist: torch
Requires-Dist: torch-geometric
Requires-Dist: tqdm
Requires-Dist: xgboost
Requires-Dist: yacs
